Workbook

Sheet CONCILIAÇÃO FINANCEIRA - GECOV
B3: CONCILIAÇÃO FINANCEIRA - GECOV
B5: MOVIMENTAÇÃO FINANCEIRA
B6: Convênio:
B7: Convenente:
B8: Vigência:
B9: CC:
B10: Data | C10: Item | D10: Entrada | E10: Saída | F10: Saldo | G10: Aplicação | H10: Resgate | I10: Rendimentos | J10: Tarifa Paga | K10: Tarifa Devolvida | L10: Saldo de tarifa
D11: 0 | E11: 0 | F11: =D11-E11 -> 0 | G11: =IF($G$10=C11,E11,"-") -> - | H11: =IF($H$10=C11,D11,"-") -> - | J11: =IF("Tarifa"=C11,E11,"-") -> - | K11: =IF("Tarifa"=C11,D11,"-") -> -
D12: 0 | E12: 0 | F12: =F11+D12-E12 -> 0 | G12: =IF($G$10=C12,E12,"-") -> - | H12: =IF($H$10=C12,D12,"-") -> - | J12: =IF("Tarifa"=C12,E12,"-") -> - | K12: =IF("Tarifa"=C12,D12,"-") -> -
D13: 0 | E13: 0 | F13: =F12+D13-E13 -> 0 | G13: =IF($G$10=C13,E13,"-") -> - | H13: =IF($H$10=C13,D13,"-") -> - | J13: =IF("Tarifa"=C13,E13,"-") -> - | K13: =IF("Tarifa"=C13,D13,"-") -> -
D14: 0 | E14: 0 | F14: =F13+D14-E14 -> 0 | G14: =IF($G$10=C14,E14,"-") -> - | H14: =IF($H$10=C14,D14,"-") -> - | J14: =IF("Tarifa"=C14,E14,"-") -> - | K14: =IF("Tarifa"=C14,D14,"-") -> -
D15: 0 | E15: 0 | F15: =F14+D15-E15 -> 0 | G15: =IF($G$10=C15,E15,"-") -> - | H15: =IF($H$10=C15,D15,"-") -> - | J15: =IF("Tarifa"=C15,E15,"-") -> - | K15: =IF("Tarifa"=C15,D15,"-") -> -
D16: 0 | E16: 0 | F16: =F15+D16-E16 -> 0 | G16: =IF($G$10=C16,E16,"-") -> - | H16: =IF($H$10=C16,D16,"-") -> - | J16: =IF("Tarifa"=C16,E16,"-") -> - | K16: =IF("Tarifa"=C16,D16,"-") -> -
D17: 0 | E17: 0 | F17: =F16+D17-E17 -> 0 | G17: =IF($G$10=C17,E17,"-") -> - | H17: =IF($H$10=C17,D17,"-") -> - | J17: =IF("Tarifa"=C17,E17,"-") -> - | K17: =IF("Tarifa"=C17,D17,"-") -> -
D18: 0 | E18: 0 | F18: =F17+D18-E18 -> 0 | G18: =IF($G$10=C18,E18,"-") -> - | H18: =IF($H$10=C18,D18,"-") -> - | J18: =IF("Tarifa"=C18,E18,"-") -> - | K18: =IF("Tarifa"=C18,D18,"-") -> -
D19: 0 | E19: 0 | F19: =F18+D19-E19 -> 0 | G19: =IF($G$10=C19,E19,"-") -> - | H19: =IF($H$10=C19,D19,"-") -> - | J19: =IF("Tarifa"=C19,E19,"-") -> - | K19: =IF("Tarifa"=C19,D19,"-") -> -
D20: 0 | E20: 0 | F20: =F19+D20-E20 -> 0 | G20: =IF($G$10=C20,E20,"-") -> - | H20: =IF($H$10=C20,D20,"-") -> - | J20: =IF("Tarifa"=C20,E20,"-") -> - | K20: =IF("Tarifa"=C20,D20,"-") -> -
D21: 0 | E21: 0 | F21: =F20+D21-E21 -> 0 | G21: =IF($G$10=C21,E21,"-") -> - | H21: =IF($H$10=C21,D21,"-") -> - | J21: =IF("Tarifa"=C21,E21,"-") -> - | K21: =IF("Tarifa"=C21,D21,"-") -> -
D22: 0 | E22: 0 | F22: =F21+D22-E22 -> 0 | G22: =IF($G$10=C22,E22,"-") -> - | H22: =IF($H$10=C22,D22,"-") -> - | J22: =IF("Tarifa"=C22,E22,"-") -> - | K22: =IF("Tarifa"=C22,D22,"-") -> -
D23: 0 | E23: 0 | F23: =F22+D23-E23 -> 0 | G23: =IF($G$10=C23,E23,"-") -> - | H23: =IF($H$10=C23,D23,"-") -> - | J23: =IF("Tarifa"=C23,E23,"-") -> - | K23: =IF("Tarifa"=C23,D23,"-") -> -
... D30: 0 | E30: 0 | F30: =F29+D30-E30 -> 0 | G30: =IF($G$10=C30,E30,"-") -> - | H30: =IF($H$10=C30,D30,"-") -> - | J30: =IF("Tarifa"=C30,E30,"-") -> - | K30: =IF("Tarifa"=C30,D30,"-") -> -
B31: TOTAL | D31: =SUM(D11:D30) -> 0 | E31: =SUM(E11:E30) -> 0 | F31: =F30+D31-E31 -> 0 | G31: =SUM(G11:G30) -> 0 | H31: =SUM(H11:H30) -> 0 | I31: =H31-G31 -> 0 | J31: =SUM(J11:J30) -> 0 | K31: =SUM(K11:K30) -> 0 | L31: =J31-K31 -> 0
B33: CONTRATO EMPRESA:
B34: NF FLS | C34: NE | D34: NF | E34: DATA | F34: VALOR BRUTO | G34: INSS | H34: IR | I34: ISS | J34: LÍQUIDO | K34: DATA PG | L34: ISS FLS | M34: INSS FLS
J35: =F35-G35-H35-I35 -> 0
J36: =F36-G36-H36-I36 -> 0
J37: =F37-G37-H37-I37 -> 0
J38: =F38-G38-H38-I38 -> 0
J39: =F39-G39-H39-I39 -> 0
J40: =F40-G40-H40-I40 -> 0
J41: =F41-G41-H41-I41 -> 0
B42: TOTAL | F42: =SUM(F35:F41) -> 0 | G42: =SUM(G35:G41) -> 0 | H42: =SUM(H35:H41) -> 0 | I42: =SUM(I35:I41) -> 0 | J42: =F42-G42-H42-I42 -> 0
C44: PREVISÃO PT | E44: % | F44: REPASSADO | G44: EXECUTADO | H44: SALDO REPASSE | I44: RENDIMENTO | J44: SALDO | M44: Dados básicos da correção pela Selic
C45: CONCEDENTE | E45: =D45/D47 -> #DIV/0! | G45: =G47*E45 -> #DIV/0! | H45: =F45-G45 -> #DIV/0! | I45: =I47*E45 -> #DIV/0! | J45: =F45+I45-G45 -> #DIV/0!
C46: CONVENENTE | E46: =D46/D47 -> #DIV/0! | G46: =G47*E46 -> #DIV/0! | H46: =F46-G46 -> #DIV/0! | I46: =I47*E46 -> #DIV/0! | J46: =F46+I46-G46 -> #DIV/0!
C47: TOTAL | D47: =SUM(D45:D46) -> 0 | E47: =SUM(E45:E46) -> #DIV/0! | F47: =SUM(F45:F46) -> 0 | G47: =F42 -> 0 | H47: =SUM(H45:H46) -> #DIV/0! | I47: =I31 -> 0 | J47: =SUM(J45:J46) -> #DIV/0!
B50: PROPORCIONALIDADE | C50: SALDO | D50: REND NÃO APLIC | E50: REND TARIFA | F50: NOTA TÉCNICA | G50: REND. NOTA TÉC | H50: ATRASO DEV. | I50: TOTAL | J50: SALDO DEVOLVIDO | K50: Dev. Maior/Menor
B51: CONCEDENTE - % | C51: =J45 -> #DIV/0! | D51: =D53*E45 -> #DIV/0! | E51: =E53*E45 -> #DIV/0! | F51: =F53*E45 -> #DIV/0! | G51: =G53*E45 -> #DIV/0! | H51: =H53*E45 -> #DIV/0! | I51: =SUM(B51:H51) -> #DIV/0! | K51: =I51-J51 -> #DIV/0!
B52: CONVENENTE - % | C52: =J46 -> #DIV/0! | D52: =D53*E46 -> #DIV/0! | E52: =E53*E46 -> #DIV/0! | F52: =F53*E46 -> #DIV/0! | G52: =G53*E46 -> #DIV/0! | H52: =H53*E46 -> #DIV/0! | I52: =SUM(B52:H52) -> #DIV/0!
B53: TOTAL | C53: =J47 -> #DIV/0! | D53: =L73 -> 0 | E53: =I94 -> 0 | F53: =F102 -> 0 | G53: =J102 -> 0 | H53: =D109 -> 0 | I53: =SUM(I51:I52) -> #DIV/0!
B55: SALDO DEVEDOR APURADO | D55: OUTRAS DEVOLUÇÕES (SE HOUVER)
B56: Data | C56: Valor | D56: Valor Devolvido | E56: Data da Devolução | F56: Percentual Calculadora Cidadão (POUP ou CDI) | G56: Rendimento | H56: Saldo Devedor Atualizado | I56: Dev. Maior/Menor
B57: =J49 -> 0 | C57: =K51 -> #DIV/0! | G57: =C57*F57 -> #DIV/0! | H57: =C57+G57 -> #DIV/0! | I57: =H57-D57 -> #DIV/0!
B58: =E57 -> 0 | C58: =I57 -> #DIV/0! | G58: =C58*F58 -> #DIV/0! | H58: =C58+G58 -> #DIV/0! | I58: =H58-D58 -> #DIV/0!
G59: =C59*F59 -> 0 | H59: =C59+G59 -> 0 | I59: =H59-D59 -> 0
G60: =C60*F60 -> 0 | H60: =C60+G60 -> 0 | I60: =H60-D60 -> 0
G61: =C61*F61 -> 0 | H61: =C61+G61 -> 0 | I61: =H61-D61 -> 0
B64: CÁLCULO DO VALOR NÃO APLICADO | J64: ATUALIZAÇÃO
B65: Histórico | C65: Data Inicial | D65: Data da aplicação ou interrupção | E65: Valor não aplicado | F65: Dias não aplicado | G65: POUP ou CDI | H65: Valor percentual da calculadora cidadão | I65: Valor do rendimento se tivesse sido aplicado (Dano) | J65: Referencia: Poup ou Selic (data da devolução) | K65: Valor calculado | L65: Valor atualizado
F66: =IF(C66=0,"",D66-C66) | G66: =IF(F66="","",IF(F66<30,"CDI","POUP")) | I66: =IF(C66=0,0,+E66*H66) -> 0 | K66: =(+I66)*J66 -> 0 | L66: =+I66+K66 -> 0
F67: =IF(C67=0,"",D67-C67) | G67: =IF(F67="","",IF(F67<30,"CDI","POUP")) | I67: =IF(C67=0,0,+E67*H67) -> 0 | K67: =(+I67)*J67 -> 0 | L67: =+I67+K67 -> 0
F68: =IF(C68=0,"",D68-C68) | G68: =IF(F68="","",IF(F68<30,"CDI","POUP")) | I68: =IF(C68=0,0,+E68*H68) -> 0 | K68: =(+I68)*J68 -> 0 | L68: =+I68+K68 -> 0
F69: =IF(C69=0,"",D69-C69) | G69: =IF(F69="","",IF(F69<30,"CDI","POUP")) | I69: =IF(C69=0,0,+E69*H69) -> 0 | K69: =(+I69)*J69 -> 0 | L69: =+I69+K69 -> 0
F70: =IF(C70=0,"",D70-C70) | G70: =IF(F70="","",IF(F70<30,"CDI","POUP")) | I70: =IF(C70=0,0,+E70*H70) -> 0 | K70: =(+I70)*J70 -> 0 | L70: =+I70+K70 -> 0
F71: =IF(C71=0,"",D71-C71) | G71: =IF(F71="","",IF(F71<30,"CDI","POUP")) | I71: =IF(C71=0,0,+E71*H71) -> 0 | K71: =(+I71)*J71 -> 0 | L71: =+I71+K71 -> 0
F72: =IF(C72=0,"",D72-C72) | G72: =IF(F72="","",IF(F72<30,"CDI","POUP")) | I72: =IF(C72=0,0,+E72*H72) -> 0 | K72: =(+I72)*J72 -> 0 | L72: =+I72+K72 -> 0
B73: TOTAL NÃO APLICADO | I73: =SUM(I66:I72) -> 0 | J73: TOTAL | L73: =SUM(L66:L72) -> 0
B76: TARIFA BANCÁRIA
B77: Histórico | C77: Data Inicial | D77: Data da aplicação (DATA DEVOLUÇÃO) | E77: Valor não aplicado | F77: Dias não aplicado | G77: POUP ou CDI | H77: Valor percentual da calculadora cidadão | I77: Valor do rendimento se tivesse sido aplicado (Dano)
B78: TARIFA | F78: =IF(C78=0,"",D78-C78) | G78: =IF(F78="","",IF(F78<30,"CDI","POUP")) | I78: =IF(C78=0,0,+E78*H78) -> 0
F79: =IF(C79=0,"",D79-C79) | G79: =IF(F79="","",IF(F79<30,"CDI","POUP")) | I79: =IF(C79=0,0,+E79*H79) -> 0
F80: =IF(C80=0,"",D80-C80) | G80: =IF(F80="","",IF(F80<30,"CDI","POUP")) | I80: =IF(C80=0,0,+E80*H80) -> 0
F81: =IF(C81=0,"",D81-C81) | G81: =IF(F81="","",IF(F81<30,"CDI","POUP")) | I81: =IF(C81=0,0,+E81*H81) -> 0
F82: =IF(C82=0,"",D82-C82) | G82: =IF(F82="","",IF(F82<30,"CDI","POUP")) | I82: =IF(C82=0,0,+E82*H82) -> 0
F83: =IF(C83=0,"",D83-C83) | G83: =IF(F83="","",IF(F83<30,"CDI","POUP")) | I83: =IF(C83=0,0,+E83*H83) -> 0
F84: =IF(C84=0,"",D84-C84) | G84: =IF(F84="","",IF(F84<30,"CDI","POUP")) | I84: =IF(C84=0,0,+E84*H84) -> 0
F85: =IF(C85=0,"",D85-C85) | G85: =IF(F85="","",IF(F85<30,"CDI","POUP")) | I85: =IF(C85=0,0,+E85*H85) -> 0
F86: =IF(C86=0,"",D86-C86) | G86: =IF(F86="","",IF(F86<30,"CDI","POUP")) | I86: =IF(C86=0,0,+E86*H86) -> 0
F87: =IF(C87=0,"",D87-C87) | G87: =IF(F87="","",IF(F87<30,"CDI","POUP")) | I87: =IF(C87=0,0,+E87*H87) -> 0
F88: =IF(C88=0,"",D88-C88) | G88: =IF(F88="","",IF(F88<30,"CDI","POUP")) | I88: =IF(C88=0,0,+E88*H88) -> 0
F89: =IF(C89=0,"",D89-C89) | G89: =IF(F89="","",IF(F89<30,"CDI","POUP")) | I89: =IF(C89=0,0,+E89*H89) -> 0
F90: =IF(C90=0,"",D90-C90) | G90: =IF(F90="","",IF(F90<30,"CDI","POUP")) | I90: =IF(C90=0,0,+E90*H90) -> 0
... F93: =IF(C93=0,"",D93-C93) | G93: =IF(F93="","",IF(F93<30,"CDI","POUP")) | I93: =IF(C93=0,0,+E93*H93) -> 0
B94: VR. TARIFA BANCÁRIA | G94: ATUALIZAÇÃO | I94: =SUM(I78:I93) -> 0
B97: NOTA TÉCNICA
B98: Histórico | C98: Nota Fiscal | D98: Data Inicial - (emissão NF) | E98: Data da aplicação (DATA DEVOLUÇÃO) | F98: Valor não aplicado | G98: Dias não aplicado | H98: POUP ou CDI | I98: Valor percentual da calculadora cidadão | J98: Valor do rendimento se tivesse sido aplicado (Dano)
B99: 1ª Medição | G99: =IF(D99=0,"",E99-D99) | H99: =IF(G99="","",IF(G99<30,"CDI","POUP")) | J99: =IF(D99=0,0,+F99*I99) -> 0
B100: 2ª Medição | G100: =IF(D100=0,"",E100-D100) | H100: =IF(G100="","",IF(G100<30,"CDI","POUP")) | J100: =IF(D100=0,0,+F100*I100) -> 0
G101: =IF(D101=0,"",E101-D101) | H101: =IF(G101="","",IF(G101<30,"CDI","POUP")) | J101: =IF(D101=0,0,+F101*I101) -> 0
B102: VR. NOTA TÉCNICA | F102: =SUM(F99:F101) -> 0 | G102: ATUALIZAÇÃO | J102: =SUM(J99:J101) -> 0
B104: DEVOLUÇÃO ATRASO - SELIC
B105: Data: 31/12/2014 | C105: Vr Extrato
B106: 31/12/14 A 02/02/15 | C106: Atualização
C107: Vr. Dev. Atualizado | D107: =SUM(D105:D106) -> 0
B108: Data: 02/02/2015 | C108: Vr. Devolvido
B109: Atualização apurada | D109: =D107-D108 -> 0
C112: onde irá extrair informações para a planilha GECON.
B115: DEMONSTRATIVO FINANCEIRO (DF)
B116: Receitas | C116: Valor
B117: Concedente | C117: =F45 -> 0
B118: Contrapartida | C118: =F46 -> 0
B119: Rendimentos | C119: =I31 -> 0
B120: Recursos Próprios Convenente (com T.A. formalizada) | C120: 0
B121: Outras Receitas formalizadas - | C121: 0
B122: Total de receitas | C122: =SUM(C117:D121) -> 0
B123: (-) Despesas | C123: Valor
B124: Cheques | C124: 0
B125: TED’S – Depósito Bancário | C125: =G47 -> 0
B126: Total Despesas | C126: =SUM(C124:D125) -> 0
B127: (=) SALDO | C127: =C122-C126 -> 0
...

Sheet GECON
B3: Informações Financeiras do Convênio - GECON
B4: Convenente | C4: ='CONCILIAÇÃO FINANCEIRA - GECOV'!C8:E8 -> 0
B5: Nº do Convênio | C5: ='CONCILIAÇÃO FINANCEIRA - GECOV'!C6 -> 0
B6: Participantes | C6: Valor Repassado | D6: Participação % | E6: Despesa Realizada | F6: Rendimento | G6: Rendimento Selic | H6: Devolução realizada (I) | K6: Devolução devida em função da proporcionalidade dos recursos (II) | N6: Saldo a devolver/(receber) para o convenente (III) = (I) - (II) - (IV)
H7: Principal | I7: Rendimento | J7: Total | K7: Principal | L7: Rendimento | M7: Total | N7: Principal | O7: Rendimento | P7: Total
B8: MGI | C8: ='CONCILIAÇÃO FINANCEIRA - GECOV'!D45 -> 0 | D8: =C8/C10*100 -> #DIV/0! | E8: =E10*D8% -> #DIV/0! | F8: =F10*D8% -> #DIV/0! | G8: =E20 -> #DIV/0! | H8: =IF(J8*(C8-E8)/(C8-E8+F8+G8)>0,J8*(C8-E8)/(C8-E8+F8+G8),0) -> #DIV/0! | I8: =IF(C8>E8,J8*(F8+G8)/(C8-E8+F8+G8),E21) -> #DIV/0! | J8: =E21 -> 0 | K8: =IF(C8-E8>0,C8-E8,0) -> #DIV/0! | L8: =IF(C8>E8,F8+G8,F8+G8+C8-E8) -> #DIV/0! | M8: =K8+L8 -> #DIV/0! | N8: =H8-K8 -> #DIV/0! | O8: =I8-L8-E17-E18 -> #DIV/0! | P8: =J8-M8-E17-E18 -> #DIV/0!
B9: Municipio | C9: ='CONCILIAÇÃO FINANCEIRA - GECOV'!D46 -> 0 | D9: =C9/C10*100 -> #DIV/0! | E9: =E10*D9% -> #DIV/0! | F9: =F10*D9% -> #DIV/0! | G9: 0 | N9: =H9-K9 -> 0 | O9: =I9-L9 -> 0 | P9: =J9-M9 -> 0
B10: Total | C10: =C8+C9 -> 0 | D10: =D8+D9 -> #DIV/0! | E10: ='CONCILIAÇÃO FINANCEIRA - GECOV'!G47 -> 0 | F10: ='CONCILIAÇÃO FINANCEIRA - GECOV'!I31 -> 0 | G10: =G8+G9 -> #DIV/0! | H10: =H8+H9 -> #DIV/0! | I10: =I8+I9 -> #DIV/0! | J10: =J8+J9 -> 0 | K10: =K8+K9 -> #DIV/0! | L10: =L8+L9 -> #DIV/0! | M10: =K10+L10 -> #DIV/0! | N10: =H10-K10 -> #DIV/0! | O10: =I10-L10-E17-E18 -> #DIV/0! | P10: =J10-M10-E17-E18 -> #DIV/0!
B13: Informações Financeiras do Convênio
B14: Valor repassado ao convenente | E14: =C8 -> 0
B15: Contrapartida | E15: =C9 -> 0 | I15: Quadro I
B16: Despesa realizada | E16: ='CONCILIAÇÃO FINANCEIRA - GECOV'!F42 -> 0 | I16: Devolução realizada pelo Convenente | M16: =M20+M21 -> 0
B17: Despesa não autorizada (IV) | E17: ='CONCILIAÇÃO FINANCEIRA - GECOV'!F51 -> #DIV/0! | I17: DAE - recurso transferido para MGI
B18: Tarifas Bancarias Indevidas (IV)* | I18: DAE - recurso com EMG
B19: Rendimento do repasse | E19: ='CONCILIAÇÃO FINANCEIRA - GECOV'!I31 -> 0 | I19: Recurso Transferido direto para MGI | M19: =M20-M17-M18 -> 0
B20: Rendimento Selic | E20: ='CONCILIAÇÃO FINANCEIRA - GECOV'!D51+'CONCILIAÇÃO FINANCEIRA - GECOV'!E51+'CONCILIAÇÃO FINANCEIRA - GECOV'!G51+'CONCILIAÇÃO FINANCEIRA - GECOV'!H51+'CONCILIAÇÃO FINANCEIRA - GECOV'!G57+'CONCILIAÇÃO FINANCEIRA - GECOV'!G58 -> #DIV/0! | I20: ¬ Recurso Devolvido | M20: ='CONCILIAÇÃO FINANCEIRA - GECOV'!J51+'CONCILIAÇÃO FINANCEIRA - GECOV'!M51+'CONCILIAÇÃO FINANCEIRA - GECOV'!D57+'CONCILIAÇÃO FINANCEIRA - GECOV'!D58 -> 0
B21: Devolução Realizada pelo Convenente (Quadro I ) | E21: =M16 -> 0
B22: * apenas tarifas não estornadas ou não devolvidas à conta do Convênio
B24: Contabilizações
B25: Receita de rendimentos sobre aplicações na convenente | E25: =IF(E8>C8,F8+G8+C8-E8,F8+G8)+E18 -> #DIV/0!
B26: Baixa de Obrigações por Repasse | E26: =IF(C8>E8,E8,C8)-E17 -> #DIV/0! | I26: Preencher apenas as abas em amarelo
B27: Baixa Contábil - Redução do capital integralizado - mediante aprovação do CA (1) | E27: =IF(E26+K8=E14,E26+K8,C8) -> #DIV/0!
B28: (1)Repasse realizado - Parte Concedente
B31: Destinação dos recursos devolvidos
B32: MGI | E32: =L8+E18 -> #DIV/0! | S32: Valor Repassado | T32: =E14 -> 0
B33: Devolução ao Estado de MG | E33: =K8+E17 -> #DIV/0! | S33: Despesa Proporcional | T33: =E8 -> #DIV/0! | U33: =T32-T33 -> #DIV/0!
B34: Recursos remanescentes da transação - Devolução devida (II) | E34: =E32+E33 -> #DIV/0! | S34: Rendimento Proporcional | T34: =F8 -> #DIV/0! | U34: 2966.4
B35: Devolução recebida a maior - pgto para convenente (III) | E35: =IF(P8>0,P8,0) -> #DIV/0! | S35: Rendimento Selic | T35: =G8 -> #DIV/0!
B36: Devolução recebida a menor - receber do convenente (III) | E36: =IF(P8<0,-P10,0) -> #DIV/0! | S36: Despesa não autorizada | T36: =E17+E18 -> #DIV/0!
B37: Recursos remanescentes da transação - Devolução realizada (I) | E37: =E34+E35-E36 -> #DIV/0!
S38: Devolução | T38: =E21 -> 0
S40: Saldo a( Devolver) ou Receber | T40: =T32-T33+T34+T35-T38+T36 -> #DIV/0! | U40: =IF(-T40=P10,"OK","****erro****") -> #DIV/0!
