Workbook

Sheet CONCILIAÇÃO FINANCEIRA - GECOV
B3: CONCILIAÇÃO FINANCEIRA - GECOV
B5: MOVIMENTAÇÃO FINANCEIRA
B6: Convênio: | C6: 650/2014
B7: Convenente: | C7: SERRA DA SAUDADE | F7: Vigência:
B8: CC:
B9: Data | C9: Item | D9: Entrada | E9: Saída | F9: Saldo | G9: Aplicação | H9: Resgate | I9: Rendimentos | J9: Tarifa Paga | K9: Tarifa Devolvida | L9: Tarifa a Devolver
F10: =D10-E10 -> 0 | G10: =IF($G$9=C10,E10,"-") -> - | H10: =IF($H$9=C10,D10,"-") -> - | J10: =IF("Tarifa"=C10,E10,"-") -> - | K10: =IF("Tarifa"=C10,D10,"-") -> -
F11: =F10+D11-E11 -> 0 | G11: =IF($G$9=C11,E11,"-") -> - | H11: =IF($H$9=C11,D11,"-") -> - | J11: =IF("Tarifa"=C11,E11,"-") -> - | K11: =IF("Tarifa"=C11,D11,"-") -> -
F12: =F11+D12-E12 -> 0 | G12: =IF($G$9=C12,E12,"-") -> - | H12: =IF($H$9=C12,D12,"-") -> - | J12: =IF("Tarifa"=C12,E12,"-") -> - | K12: =IF("Tarifa"=C12,D12,"-") -> -
F13: =F12+D13-E13 -> 0 | G13: =IF($G$9=C13,E13,"-") -> - | H13: =IF($H$9=C13,D13,"-") -> - | J13: =IF("Tarifa"=C13,E13,"-") -> - | K13: =IF("Tarifa"=C13,D13,"-") -> -
F14: =F13+D14-E14 -> 0 | G14: =IF($G$9=C14,E14,"-") -> - | H14: =IF($H$9=C14,D14,"-") -> - | J14: =IF("Tarifa"=C14,E14,"-") -> - | K14: =IF("Tarifa"=C14,D14,"-") -> -
F15: =F14+D15-E15 -> 0 | G15: =IF($G$9=C15,E15,"-") -> - | H15: =IF($H$9=C15,D15,"-") -> - | I15: =H45-G45 -> 0 | J15: =IF("Tarifa"=C15,E15,"-") -> - | K15: =IF("Tarifa"=C15,D15,"-") -> -
F16: =F15+D16-E16 -> 0 | G16: =IF($G$9=C16,E16,"-") -> - | H16: =IF($H$9=C16,D16,"-") -> - | J16: =IF("Tarifa"=C16,E16,"-") -> - | K16: =IF("Tarifa"=C16,D16,"-") -> -
F17: =F16+D17-E17 -> 0 | G17: =IF($G$9=C17,E17,"-") -> - | H17: =IF($H$9=C17,D17,"-") -> - | J17: =IF("Tarifa"=C17,E17,"-") -> - | K17: =IF("Tarifa"=C17,D17,"-") -> -
F18: =F17+D18-E18 -> 0 | G18: =IF($G$9=C18,E18,"-") -> - | H18: =IF($H$9=C18,D18,"-") -> - | J18: =IF("Tarifa"=C18,E18,"-") -> - | K18: =IF("Tarifa"=C18,D18,"-") -> -
F19: =F18+D19-E19 -> 0 | G19: =IF($G$9=C19,E19,"-") -> - | H19: =IF($H$9=C19,D19,"-") -> - | J19: =IF("Tarifa"=C19,E19,"-") -> - | K19: =IF("Tarifa"=C19,D19,"-") -> -
F20: =F19+D20-E20 -> 0 | G20: =IF($G$9=C20,E20,"-") -> - | H20: =IF($H$9=C20,D20,"-") -> - | J20: =IF("Tarifa"=C20,E20,"-") -> - | K20: =IF("Tarifa"=C20,D20,"-") -> -
F21: =F20+D21-E21 -> 0 | G21: =IF($G$9=C21,E21,"-") -> - | H21: =IF($H$9=C21,D21,"-") -> - | J21: =IF("Tarifa"=C21,E21,"-") -> - | K21: =IF("Tarifa"=C21,D21,"-") -> -
F22: =F21+D22-E22 -> 0 | G22: =IF($G$9=C22,E22,"-") -> - | H22: =IF($H$9=C22,D22,"-") -> - | J22: =IF("Tarifa"=C22,E22,"-") -> - | K22: =IF("Tarifa"=C22,D22,"-") -> -
F23: =F22+D23-E23 -> 0 | G23: =IF($G$9=C23,E23,"-") -> - | H23: =IF($H$9=C23,D23,"-") -> - | J23: =IF("Tarifa"=C23,E23,"-") -> - | K23: =IF("Tarifa"=C23,D23,"-") -> -
F24: =F23+D24-E24 -> 0 | G24: =IF($G$9=C24,E24,"-") -> - | H24: =IF($H$9=C24,D24,"-") -> - | J24: =IF("Tarifa"=C24,E24,"-") -> - | K24: =IF("Tarifa"=C24,D24,"-") -> -
F25: =F24+D25-E25 -> 0 | G25: =IF($G$9=C25,E25,"-") -> - | H25: =IF($H$9=C25,D25,"-") -> - | J25: =IF("Tarifa"=C25,E25,"-") -> - | K25: =IF("Tarifa"=C25,D25,"-") -> -
F26: =F25+D26-E26 -> 0 | G26: =IF($G$9=C26,E26,"-") -> - | H26: =IF($H$9=C26,D26,"-") -> - | J26: =IF("Tarifa"=C26,E26,"-") -> - | K26: =IF("Tarifa"=C26,D26,"-") -> -
F27: =F26+D27-E27 -> 0 | G27: =IF($G$9=C27,E27,"-") -> - | H27: =IF($H$9=C27,D27,"-") -> - | J27: =IF("Tarifa"=C27,E27,"-") -> - | K27: =IF("Tarifa"=C27,D27,"-") -> -
... F44: =F43+D44-E44 -> 0 | G44: =IF($G$9=C44,E44,"-") -> - | H44: =IF($H$9=C44,D44,"-") -> - | J44: =IF("Tarifa"=C44,E44,"-") -> - | K44: =IF("Tarifa"=C44,D44,"-") -> -
B45: TOTAL | D45: =SUM(D10:D44) -> 0 | E45: =SUM(E10:E44) -> 0 | F45: =F44+D45-E45 -> 0 | G45: =SUM(G10:G44) -> 0 | H45: =SUM(H10:H44) -> 0 | I45: 0 | J45: =SUM(J10:J44) -> 0 | K45: =SUM(K10:K44) -> 0 | L45: =J45-K45 -> 0
B47: CONTRATO EMPRESA:
B48: NF FLS | C48: NE | D48: NF | E48: DATA | F48: VALOR BRUTO | G48: INSS | H48: IR | I48: ISS | J48: LÍQUIDO | K48: DATA PG | L48: ISS FLS | M48: INSS FLS
J49: =F49-G49-H49-I49 -> 0
J50: =F50-G50-H50-I50 -> 0
J51: =F51-G51-H51-I51 -> 0
J52: =F52-G52-H52-I52 -> 0
J53: =F53-G53-H53-I53 -> 0
B54: TOTAL | F54: =SUM(F49:F53) -> 0 | G54: =SUM(G49:G53) -> 0 | H54: =SUM(H49:H53) -> 0 | I54: =SUM(I49:I53) -> 0 | J54: =F54-G54-H54-I54 -> 0
C55: INEXECUÇÃO
C56: VR. REPASSADO | E56: % | M56: Dados básicos da correção pela Selic
C57: CONCEDENTE | D57: 0 | E57: =D57/D59 -> #DIV/0! | G57: =G59*E57 -> #DIV/0! | H57: =F57-G57 -> #DIV/0!
C58: CONVENENTE | D58: 0 | E58: =D58/D59 -> #DIV/0! | G58: =G59*E58 -> #DIV/0! | H58: =F58-G58 -> #DIV/0!
C59: TOTAL | D59: =SUM(D57:D58) -> 0 | E59: =SUM(E57:E58) -> #DIV/0! | F59: =SUM(F57:F58) -> 0 | G59: =F54 -> 0 | H59: =SUM(H57:H58) -> #DIV/0!
M61: VR. DATA DEVOLUÇÃO
C62: Proporcionalidade | D62: SALDO CV | E62: RENDIMENTO | F62: REND NÃO APLIC | G62: REND TARIFA | H62: NOTA TÉCNICA | I62: REND. NT | J62: ATRASO DEV. | K62: TOTAL | L62: Devolvido | M62: Dev. Maior/Menor
C63: CONCEDENTE - % | D63: =D59 -> 0 | E63: =E65*E57 -> #DIV/0! | F63: =F65*E57 -> #DIV/0! | G63: =G65*E57 -> #DIV/0! | H63: =H65*E57 -> #DIV/0! | I63: =I65*E57 -> #DIV/0! | J63: =J65*E57 -> #DIV/0! | K63: =SUM(D63:J63) -> #DIV/0! | L63: 0 | M63: =K63-L63 -> #DIV/0!
C64: CONVENENTE - % | D64: =H58 -> #DIV/0! | E64: =E65*E58 -> #DIV/0! | F64: =F65*E58 -> #DIV/0! | G64: =G65*E58 -> #DIV/0! | H64: =H65*E58 -> #DIV/0! | I64: =I65*E58 -> #DIV/0! | J64: =J65*E58 -> #DIV/0! | K64: =SUM(D64:J64) -> #DIV/0!
C65: TOTAL | D65: =SUM(D63:D64) -> #DIV/0! | E65: =I45 -> 0 | F65: =L74 -> 0 | G65: =I82 -> 0 | H65: =F90 -> 0 | I65: =J90 -> 0 | J65: =D97 -> 0 | K65: =SUM(K63) -> #DIV/0!
B67: CÁLCULO DO VALOR NÃO APLICADO - INEXECUÇÃO | J67: ATUALIZAÇÃO
B68: Histórico | C68: Data Inicial | D68: Data da aplicação ou interrupção | E68: Valor não aplicado | F68: Dias não aplicado | G68: SELIC | H68: Valor percentual da calculadora cidadão | I68: Valor do rendimento se tivesse sido aplicado (Dano) | J68: Referencia: SELIC | K68: Valor calculado | L68: Valor atualizado
B69: 1º Repasse | C69: =B10 -> 0 | D69: =B13 -> 0 | E69: =D57 -> 0 | F69: =IF(C69=0,"",D69-C69) | G69: SELIC | H69: 0.35 | I69: =IF(C69=0,0,+E69*H69) -> 0 | K69: =(+I69)*J69 -> 0 | L69: =+I69+K69 -> 0
B70: 2º Repasse | F70: =IF(C70=0,"",D70-C70) | G70: =IF(F70="","",IF(F70<30,"CDI","POUP")) | I70: =IF(C70=0,0,+E70*H70) -> 0 | K70: =(+I70)*J70 -> 0 | L70: =+I70+K70 -> 0
B71: 1º Contrap | F71: =IF(C71=0,"",D71-C71) | G71: =IF(F71="","",IF(F71<30,"CDI","POUP")) | I71: =IF(C71=0,0,+E71*H71) -> 0 | K71: =(+I71)*J71 -> 0 | L71: =+I71+K71 -> 0
B72: 2ª Contrap | F72: =IF(C72=0,"",D72-C72) | G72: =IF(F72="","",IF(F72<30,"CDI","POUP")) | I72: =IF(C72=0,0,+E72*H72) -> 0 | K72: =(+I72)*J72 -> 0 | L72: =+I72+K72 -> 0
B73: Saldo conta | F73: =IF(C73=0,"",D73-C73) | G73: =IF(F73="","",IF(F73<30,"CDI","POUP")) | I73: =IF(C73=0,0,+E73*H73) -> 0 | K73: =(+I73)*J73 -> 0 | L73: =+I73+K73 -> 0
B74: TOTAL NÃO APLICADO | I74: =SUM(I69:I73) -> 0 | J74: TOTAL | L74: =SUM(L69:L73) -> 0
B77: TARIFA BANCÁRIA
B78: Histórico | C78: Data Inicial | D78: Data da aplicação (DATA DEVOLUÇÃO) | E78: Valor não aplicado | F78: Dias não aplicado | G78: POUP ou CDI | H78: Valor percentual da calculadora cidadão | I78: Valor do rendimento se tivesse sido aplicado (Dano)
B79: TARIFA | F79: =IF(C79=0,"",D79-C79) | G79: =IF(F79="","",IF(F79<30,"CDI","POUP")) | I79: =IF(C79=0,0,+E79*H79) -> 0
F80: =IF(C80=0,"",D80-C80) | G80: =IF(F80="","",IF(F80<30,"CDI","POUP")) | I80: =IF(C80=0,0,+E80*H80) -> 0
F81: =IF(C81=0,"",D81-C81) | G81: =IF(F81="","",IF(F81<30,"CDI","POUP")) | I81: =IF(C81=0,0,+E81*H81) -> 0
B82: VR. TARIFA BANCÁRIA | G82: ATUALIZAÇÃO | I82: =SUM(I79:I81) -> 0
B85: NOTA TÉCNICA
B86: Histórico | C86: Nota Fiscal | D86: Data Inicial - (emissão NF) | E86: Data da aplicação (DATA DEVOLUÇÃO) | F86: Valor não aplicado | G86: Dias não aplicado | H86: POUP ou CDI | I86: Valor percentual da calculadora cidadão | J86: Valor do rendimento se tivesse sido aplicado (Dano)
B87: 1ª Medição | G87: =IF(D87=0,"",E87-D87) | H87: =IF(G87="","",IF(G87<30,"CDI","POUP")) | J87: =IF(D87=0,0,+F87*I87) -> 0
B88: 2ª Medição | G88: =IF(D88=0,"",E88-D88) | H88: =IF(G88="","",IF(G88<30,"CDI","POUP")) | J88: =IF(D88=0,0,+F88*I88) -> 0
G89: =IF(D89=0,"",E89-D89) | H89: =IF(G89="","",IF(G89<30,"CDI","POUP")) | J89: =IF(D89=0,0,+F89*I89) -> 0
B90: VR. NOTA TÉCNICA | F90: =SUM(F87:F89) -> 0 | G90: ATUALIZAÇÃO | J90: =SUM(J87:J89) -> 0
B92: DEVOLUÇÃO ATRASO - SELIC
B93: Data: 31/12/2014 | C93: Vr Extrato
B94: 31/12/14 A 02/02/15 | C94: Atualização
C95: Vr. Dev. Atualizado | D95: =SUM(D93:D94) -> 0
B96: Data: 02/02/2015 | C96: Vr. Devolvido
B97: Atualização apurada | D97: =D95-D96 -> 0
C100: onde irá extrair informações para a planilha GECON.
B136: DEMONSTRATIVO FINANCEIRO (DF)
B137: Receitas | C137: Valor
B138: Repasse MGI | C138: =D57 -> 0
B139: (+) Rendimento SELIC até xx/xx/xx
B140: (=) Valor a Devolver em xx/xx/xx | C140: =C138+C139 -> 0
B141: (-) Devolução à MGI em xx/xx/xx | C141: =L63 -> 0
B142: Saldo em xx/xx/xx | C142: =SUM(C136:D141) -> 0
B143: (+) Atualização de saldo - Valor Presente SELIC xx/xx/xx
B144: (=) Cobrança Valor Presente | C144: =C142+C143 -> 0

Sheet GECON
B3: Informações Financeiras do Convênio - GECON
B4: Convenente | C4: ='CONCILIAÇÃO FINANCEIRA - GECOV'!C7:E7 -> SERRA DA SAUDADE
B5: Nº do Convênio | C5: ='CONCILIAÇÃO FINANCEIRA - GECOV'!C6 -> 650/2014
B6: Participantes | C6: Valor Repassado | D6: Participação % | E6: Despesa Realizada | F6: Rendimento | G6: Rendimento Selic | H6: Devolução realizada (I) | K6: Devolução devida em função da proporcionalidade dos recursos (II) | N6: Saldo a devolver/(receber) para o convenente (III) = (I) - (II) - (IV)
H7: Principal | I7: Rendimento | J7: Total | K7: Principal | L7: Rendimento | M7: Total | N7: Principal | O7: Rendimento | P7: Total
B8: MGI | C8: ='CONCILIAÇÃO FINANCEIRA - GECOV'!D57 -> 0 | D8: =C8/C10*100 -> #DIV/0! | E8: =E10*D8% -> #DIV/0! | F8: =F10*D8% -> #DIV/0! | G8: =E20 -> #DIV/0! | H8: =IF(J8*(C8-E8)/(C8-E8+F8+G8)>0,J8*(C8-E8)/(C8-E8+F8+G8),0) -> #DIV/0! | I8: =IF(C8>E8,J8*(F8+G8)/(C8-E8+F8+G8),E21) -> #DIV/0! | J8: =E21 -> 0 | K8: =IF(C8-E8>0,C8-E8,0) -> #DIV/0! | L8: =IF(C8>E8,F8+G8,F8+G8+C8-E8) -> #DIV/0! | M8: =K8+L8 -> #DIV/0! | N8: =H8-K8 -> #DIV/0! | O8: =I8-L8-E17-E18 -> #DIV/0! | P8: =J8-M8-E17-E18 -> #DIV/0!
B9: Municipio | C9: ='CONCILIAÇÃO FINANCEIRA - GECOV'!D58 -> 0 | D9: =C9/C10*100 -> #DIV/0! | E9: =E10*D9% -> #DIV/0! | F9: =F10*D9% -> #DIV/0! | G9: 0 | N9: =H9-K9 -> 0 | O9: =I9-L9 -> 0 | P9: =J9-M9 -> 0
B10: Total | C10: =C8+C9 -> 0 | D10: =D8+D9 -> #DIV/0! | E10: ='CONCILIAÇÃO FINANCEIRA - GECOV'!G59 -> 0 | F10: ='CONCILIAÇÃO FINANCEIRA - GECOV'!E65 -> 0 | G10: =G8+G9 -> #DIV/0! | H10: =H8+H9 -> #DIV/0! | I10: =I8+I9 -> #DIV/0! | J10: =J8+J9 -> 0 | K10: =K8+K9 -> #DIV/0! | L10: =L8+L9 -> #DIV/0! | M10: =K10+L10 -> #DIV/0! | N10: =H10-K10 -> #DIV/0! | O10: =I10-L10-E17-E18 -> #DIV/0! | P10: =J10-M10-E17-E18 -> #DIV/0!
B13: Informações Financeiras do Convênio
B14: Valor repassado ao convenente | E14: =C8 -> 0
B15: Contrapartida | E15: =C9 -> 0 | I15: Quadro I
B16: Despesa realizada | E16: ='CONCILIAÇÃO FINANCEIRA - GECOV'!F54 -> 0 | I16: Devolução realizada pelo Convenente | M16: =M20+M21 -> 0
B17: Despesa não autorizada (IV) | E17: ='CONCILIAÇÃO FINANCEIRA - GECOV'!H63 -> #DIV/0! | I17: DAE - recurso transferido para MGI
B18: Tarifas Bancarias Indevidas (IV)* | I18: DAE - recurso com EMG
B19: Rendimento do repasse | E19: ='CONCILIAÇÃO FINANCEIRA - GECOV'!I45 -> 0 | I19: Recurso Transferido direto para MGI | M19: =M20-M17-M18 -> 0
B20: Rendimento Selic | E20: ='CONCILIAÇÃO FINANCEIRA - GECOV'!F63+'CONCILIAÇÃO FINANCEIRA - GECOV'!G63+'CONCILIAÇÃO FINANCEIRA - GECOV'!I63+'CONCILIAÇÃO FINANCEIRA - GECOV'!J63 -> #DIV/0! | I20: ¬ Recurso Devolvido | M20: ='CONCILIAÇÃO FINANCEIRA - GECOV'!L63 -> 0
B21: Devolução Realizada pelo Convenente (Quadro I ) | E21: =M16 -> 0
B22: * apenas tarifas não estornadas ou não devolvidas à conta do Convênio
B24: Contabilizações
B25: Receita de rendimentos sobre aplicações na convenente | E25: =IF(E8>C8,F8+G8+C8-E8,F8+G8)+E18 -> #DIV/0!
B26: Baixa de Obrigações por Repasse | E26: =IF(C8>E8,E8,C8)-E17 -> #DIV/0! | I26: Preencher apenas as abas em amarelo
B27: Baixa Contábil - Redução do capital integralizado - mediante aprovação do CA (1) | E27: =IF(E26+K8=E14,E26+K8,C8) -> #DIV/0!
B28: (1)Repasse realizado - Parte Concedente
B31: Destinação dos recursos devolvidos
B32: MGI | E32: =L8+E18 -> #DIV/0! | S32: Valor Repassado | T32: =E14 -> 0
B33: Devolução ao Estado de MG | E33: =K8+E17 -> #DIV/0! | S33: Despesa Proporcional | T33: =E8 -> #DIV/0! | U33: =T32-T33 -> #DIV/0!
B34: Recursos remanescentes da transação - Devolução devida (II) | E34: =E32+E33 -> #DIV/0! | S34: Rendimento Proporcional | T34: =F8 -> #DIV/0! | U34: 2966.4
B35: Devolução recebida a maior - pgto para convenente (III) | E35: =IF(P8>0,P8,0) -> #DIV/0! | S35: Rendimento Selic | T35: =G8 -> #DIV/0!
B36: Devolução recebida a menor - receber do convenente (III) | E36: =IF(P8<0,-P10,0) -> #DIV/0! | S36: Despesa não autorizada | T36: =E17+E18 -> #DIV/0!
B37: Recursos remanescentes da transação - Devolução realizada (I) | E37: =E34+E35-E36 -> #DIV/0!
S38: Devolução | T38: =E21 -> 0
S40: Saldo a( Devolver) ou Receber | T40: =T32-T33+T34+T35-T38+T36 -> #DIV/0! | U40: =IF(-T40=P10,"OK","****erro****") -> #DIV/0!
